{
  "disclaimer": "Usage subject to terms: https://openexchangerates.org/terms",
  "license": "https://openexchangerates.org/license",
  "timestamp": 1604289600,
  "base": "USD",
  "rates": {
    "AED": 3.6732,
    "AFN": 77.030446,
    "ALL": 106.457995,
    "AMD": 481.616228,
    "ANG": 1.799668,
    "AOA": 665.506,
    "ARS": 78.4396,
    "AUD": 1.425785,
    "AWG": 1.8,
    "AZN": 1.7025,
    "BAM": 1.679942,
    "BBD": 2,
    "BDT": 85.094803,
    "BGN": 1.6793,
    "BHD": 0.377243,
    "BIF": 1939.994169,
    "BMD": 1,
    "BND": 1.367937,
    "BOB": 6.922889,
    "BRL": 5.7391,
    "BSD": 1,
    "BTC": 0.00007291651,
    "BTN": 74.746283,
    "BTS": 57.3809685039,
    "BWP": 11.432167,
    "BYN": 2.637351,
    "BZD": 2.020933,
    "CAD": 1.333703,
    "CDF": 1965.488974,
    "CHF": 0.9172,
    "CLF": 0.028025,
    "CLP": 773.299678,
    "CNH": 6.688456,
    "CNY": 6.6874,
    "COP": 3871.718746,
    "CRC": 607.972186,
    "CUC": 1.002276,
    "CUP": 25.75,
    "CVE": 94.65,
    "CZK": 23.4111,
    "DASH": 0.0146686453,
    "DJF": 178.489339,
    "DKK": 6.397749,
    "DOGE": 383.546473684,
    "DOP": 58.61718,
    "DZD": 128.950789,
    "EAC": 2867.98535556,
    "EGP": 15.7111,
    "EMC": 1.2125648612,
    "ERN": 15.000453,
    "ETB": 38.10473,
    "ETH": 0.0025018138,
    "EUR": 0.8591,
    "FCT": 0.5715065711,
    "FJD": 2.1255,
    "FKP": 0.773582,
    "FTC": 22.4451027826,
    "GBP": 0.773582,
    "GEL": 3.24,
    "GGP": 0.773582,
    "GHS": 5.8426,
    "GIP": 0.773582,
    "GMD": 51.75,
    "GNF": 9825.742716,
    "GTQ": 7.817767,
    "GYD": 209.813309,
    "HKD": 7.75465,
    "HNL": 24.626895,
    "HRK": 6.502,
    "HTG": 63.363502,
    "HUF": 314.92,
    "IDR": 14691.5,
    "ILS": 3.40655,
    "IMP": 0.773582,
    "INR": 74.427498,
    "IQD": 1196.770377,
    "IRR": 42105,
    "ISK": 141.14,
    "JEP": 0.773582,
    "JMD": 147.010656,
    "JOD": 0.709,
    "JPY": 104.674,
    "KES": 108.86,
    "KGS": 81.801901,
    "KHR": 4070.826755,
    "KMF": 421.649723,
    "KPW": 900,
    "KRW": 1134.842944,
    "KWD": 0.305667,
    "KYD": 0.835488,
    "KZT": 434.018787,
    "LAK": 9273.192748,
    "LBP": 1515.786888,
    "LD": 320,
    "LKR": 184.782507,
    "LRD": 183,
    "LSL": 16.28531,
    "LTC": 0.0179275726,
    "LYD": 1.366758,
    "MAD": 9.246065,
    "MDL": 17.102075,
    "MGA": 3949.745691,
    "MKD": 52.923617,
    "MMK": 1290.342752,
    "MNT": 2856.162511,
    "MOP": 8.006184,
    "MRO": 357,
    "MRU": 38.439636,
    "MUR": 39.98,
    "MVR": 15.41,
    "MWK": 758.194725,
    "MXN": 21.275914,
    "MYR": 4.155,
    "MZN": 73.15,
    "NAD": 16.31,
    "NGN": 381.44,
    "NIO": 34.93968,
    "NMC": 3.2262324937,
    "NOK": 9.55614,
    "NPR": 119.594734,
    "NVC": 0.3852517642,
    "NXT": 110.414893939,
    "NZD": 1.513661,
    "OMR": 0.385,
    "PAB": 1,
    "PEN": 3.62095,
    "PGK": 3.518938,
    "PHP": 48.575027,
    "PKR": 160.826855,
    "PLN": 3.960939,
    "PPC": 2.5433167196,
    "PYG": 7048.251954,
    "QAR": 3.650442,
    "RON": 4.175,
    "RSD": 100.96,
    "RUB": 79.6529,
    "RWF": 981.371532,
    "SAR": 3.7505,
    "SBD": 8.069239,
    "SCR": 19.332756,
    "SDG": 55.3,
    "SEK": 8.9003,
    "SGD": 1.367149,
    "SHP": 0.773582,
    "SLL": 9959.00017,
    "SOS": 579.961493,
    "SRD": 14.154,
    "SSP": 130.26,
    "STD": 21040.953008,
    "STN": 21.15,
    "STR": 12.7848824561,
    "SVC": 8.772276,
    "SYP": 512.609041,
    "SZL": 16.278179,
    "THB": 31.1555,
    "TJS": 10.371792,
    "TMT": 3.5,
    "TND": 2.775,
    "TOP": 2.32625,
    "TRY": 8.3829,
    "TTD": 6.816335,
    "TWD": 28.594601,
    "TZS": 2325.023915,
    "UAH": 28.538716,
    "UGX": 3749.676753,
    "USD": 1,
    "UYU": 43.053599,
    "UZS": 10387.380065,
    "VEF": 248487.642241,
    "VEF_BLKMKT": 542413.91,
    "VEF_DICOM": 506541.76,
    "VEF_DIPRO": 27616375.57,
    "VES": 518284.607513,
    "VND": 23247.364821,
    "VTC": 6.8084886676,
    "VUV": 113.801139,
    "WST": 2.630791,
    "XAF": 563.532659,
    "XAG": 0.04174497,
    "XAU": 0.00053118,
    "XCD": 2.70255,
    "XDR": 0.70823,
    "XMR": 0.0079475546,
    "XOF": 563.532659,
    "XPD": 0.00044425,
    "XPF": 102.5179,
    "XPM": 21.0235762811,
    "XPT": 0.00117787,
    "XRP": 4.1499903189,
    "YER": 250.350066,
    "ZAR": 16.233987,
    "ZMW": 20.635021,
    "ZWL": 322
  }
}