{
  "disclaimer": "Usage subject to terms: https://openexchangerates.org/terms",
  "license": "https://openexchangerates.org/license",
  "timestamp": 1563015619,
  "base": "USD",
  "rates": {
    "AED": 3.673096,
    "AFN": 80.301216,
    "ALL": 108.3,
    "AMD": 476.920824,
    "ANG": 1.780086,
    "AOA": 345.9285,
    "ARS": 41.53,
    "AUD": 1.424366,
    "AWG": 1.799996,
    "AZN": 1.7025,
    "BAM": 1.737356,
    "BBD": 2,
    "BDT": 84.496,
    "BGN": 1.736495,
    "BHD": 0.377029,
    "BIF": 1845,
    "BMD": 1,
    "BND": 1.35054,
    "BOB": 6.910107,
    "BRL": 3.7381,
    "BSD": 1,
    "BTC": 0.000088468169,
    "BTN": 68.450757,
    "BTS": 20.4022395402,
    "BWP": 10.627,
    "BYN": 2.035459,
    "BZD": 2.015748,
    "CAD": 1.30395,
    "CDF": 1665,
    "CHF": 0.983816,
    "CLF": 0.02435,
    "CLP": 679.81,
    "CNH": 6.878801,
    "CNY": 6.880846,
    "COP": 3190.866529,
    "CRC": 580.345475,
    "CUC": 1,
    "CUP": 25.75,
    "CVE": 97.8765,
    "CZK": 22.7027,
    "DASH": 0.0071706397,
    "DJF": 178,
    "DKK": 6.625,
    "DOGE": 316.963364286,
    "DOP": 50.975,
    "DZD": 119.170227,
    "EAC": 2867.98535556,
    "EGP": 16.5935,
    "EMC": 1.2125648612,
    "ERN": 14.999616,
    "ETB": 29.055,
    "ETH": 0.003720861,
    "EUR": 0.886407,
    "FCT": 0.2251731415,
    "FJD": 2.14414,
    "FKP": 0.79542,
    "FTC": 22.4451027826,
    "GBP": 0.79542,
    "GEL": 2.84,
    "GGP": 0.79542,
    "GHS": 5.41,
    "GIP": 0.79542,
    "GMD": 49.725,
    "GNF": 9230,
    "GTQ": 7.677762,
    "GYD": 209.224461,
    "HKD": 7.82455,
    "HNL": 24.694877,
    "HRK": 6.5615,
    "HTG": 93.928314,
    "HUF": 289.22,
    "IDR": 13980.539625,
    "ILS": 3.5554,
    "IMP": 0.79542,
    "INR": 68.5605,
    "IQD": 1190,
    "IRR": 42105,
    "ISK": 125.900055,
    "JEP": 0.79542,
    "JMD": 131.78,
    "JOD": 0.709004,
    "JPY": 107.915,
    "KES": 102.95,
    "KGS": 69.53165,
    "KHR": 4082.5,
    "KMF": 437.951736,
    "KPW": 900,
    "KRW": 1177.32,
    "KWD": 0.304342,
    "KYD": 0.833422,
    "KZT": 384.23,
    "LAK": 8682.5,
    "LBP": 1511.691547,
    "LD": 295.5,
    "LKR": 175.469527,
    "LRD": 199.00005,
    "LSL": 14,
    "LTC": 0.0099378882,
    "LYD": 1.396062,
    "MAD": 9.5586,
    "MDL": 17.694504,
    "MGA": 3622.5,
    "MKD": 54.653856,
    "MMK": 1510.737097,
    "MNT": 2660.147861,
    "MOP": 8.057679,
    "MRO": 357,
    "MRU": 36.775,
    "MUR": 35.8485,
    "MVR": 15.449981,
    "MWK": 755.913093,
    "MXN": 18.988315,
    "MYR": 4.113028,
    "MZN": 62.349925,
    "NAD": 14,
    "NGN": 360,
    "NIO": 33.45,
    "NMC": 3.2262324937,
    "NOK": 8.53206,
    "NPR": 109.527619,
    "NVC": 0.3852517642,
    "NXT": 40.524996347,
    "NZD": 1.493652,
    "OMR": 0.384998,
    "PAB": 1,
    "PEN": 3.288458,
    "PGK": 3.37,
    "PHP": 51.047756,
    "PKR": 158,
    "PLN": 3.7885,
    "PPC": 2.5433167196,
    "PYG": 6040.140456,
    "QAR": 3.641779,
    "RON": 4.197991,
    "RSD": 104.418694,
    "RUB": 63.051,
    "RWF": 915,
    "SAR": 3.75025,
    "SBD": 8.273502,
    "SCR": 13.65963,
    "SDG": 45.125,
    "SEK": 9.3724,
    "SGD": 1.357405,
    "SHP": 0.79542,
    "SLL": 7047.710032,
    "SOS": 584,
    "SRD": 7.458,
    "SSP": 130.26,
    "STD": 21560.79,
    "STN": 21.83,
    "STR": 10.6287116168,
    "SVC": 8.750677,
    "SYP": 515.15526,
    "SZL": 13.985,
    "THB": 30.891,
    "TJS": 9.429993,
    "TMT": 3.499986,
    "TND": 2.887002,
    "TOP": 2.28035,
    "TRY": 5.715492,
    "TTD": 6.76625,
    "TWD": 31.0525,
    "TZS": 2300,
    "UAH": 25.671,
    "UGX": 3695.102654,
    "USD": 1,
    "UYU": 35.150329,
    "UZS": 8583,
    "VEF": 248487.642241,
    "VEF_BLKMKT": 8012.71,
    "VEF_DICOM": 7144.48,
    "VEF_DIPRO": 10,
    "VES": 7128.550424,
    "VND": 23144.197089,
    "VTC": 2.5042252257,
    "VUV": 115.30049,
    "WST": 2.618578,
    "XAF": 581.444854,
    "XAG": 0.06568576,
    "XAU": 0.00070654,
    "XCD": 2.70255,
    "XDR": 0.72294,
    "XMR": 0.0109720592,
    "XOF": 581.444854,
    "XPD": 0.00064573,
    "XPF": 105.776487,
    "XPM": 5.3239197361,
    "XPT": 0.00120428,
    "XRP": 3.0235221892,
    "YER": 250.300682,
    "ZAR": 13.958699,
    "ZMW": 12.475432,
    "ZWL": 322.000001
  }
}