{
  "disclaimer": "Usage subject to terms: https://openexchangerates.org/terms",
  "license": "https://openexchangerates.org/license",
  "timestamp": 1615273200,
  "base": "USD",
  "rates": {
    "AED": 3.673011,
    "AFN": 77.599996,
    "ALL": 104.149948,
    "AMD": 523.48494,
    "ANG": 1.795728,
    "AOA": 618.3,
    "ARS": 90.4759,
    "AUD": 1.306857,
    "AWG": 1.8,
    "AZN": 1.700805,
    "BAM": 1.652065,
    "BBD": 2,
    "BDT": 84.830725,
    "BGN": 1.6494,
    "BHD": 0.377077,
    "BIF": 1950.307236,
    "BMD": 1,
    "BND": 1.351669,
    "BOB": 6.921816,
    "BRL": 5.8758,
    "BSD": 1,
    "BTC": 0.000018550358,
    "BTN": 73.188078,
    "BTS": 17.8452134615,
    "BWP": 11.244668,
    "BYN": 2.608619,
    "BZD": 2.01659,
    "CAD": 1.265615,
    "CDF": 1983.407561,
    "CHF": 0.935762,
    "CLF": 0.026692,
    "CLP": 736.499369,
    "CNH": 6.54182,
    "CNY": 6.5292,
    "COP": 3637.711532,
    "CRC": 612.546813,
    "CUC": 1,
    "CUP": 25.75,
    "CVE": 93.35,
    "CZK": 22.266007,
    "DASH": 0.0043344175,
    "DJF": 178.457114,
    "DKK": 6.271699,
    "DOGE": 17.3448803738,
    "DOP": 57.94133,
    "DZD": 133.450302,
    "EGP": 15.73,
    "ERN": 14.999675,
    "ETB": 40.363724,
    "ETH": 0.0005461467,
    "EUR": 0.843334,
    "FJD": 2.05475,
    "FKP": 0.722792,
    "GBP": 0.722792,
    "GEL": 3.33,
    "GGP": 0.722792,
    "GHS": 5.738926,
    "GIP": 0.722792,
    "GMD": 51.35,
    "GNF": 10161.435158,
    "GTQ": 7.737107,
    "GYD": 209.110957,
    "HKD": 7.76785,
    "HNL": 24.138835,
    "HRK": 6.3927,
    "HTG": 75.533636,
    "HUF": 310.089308,
    "IDR": 14425,
    "ILS": 3.337743,
    "IMP": 0.722792,
    "INR": 73.149496,
    "IQD": 1462.55743,
    "IRR": 42105,
    "ISK": 128.1,
    "JEP": 0.722792,
    "JMD": 150.01184,
    "JOD": 0.709,
    "JPY": 109.14133333,
    "KES": 109.65,
    "KGS": 84.634572,
    "KHR": 4069.863927,
    "KMF": 415.250006,
    "KPW": 900,
    "KRW": 1140.779268,
    "KWD": 0.302979,
    "KYD": 0.833713,
    "KZT": 420.169659,
    "LAK": 9379.516121,
    "LBP": 1515.878725,
    "LD": 320,
    "LKR": 196.729116,
    "LRD": 173.900005,
    "LSL": 15.528056,
    "LTC": 0.0050558673,
    "LYD": 4.485205,
    "MAD": 9.059364,
    "MDL": 17.599529,
    "MGA": 3791.781228,
    "MKD": 52.044974,
    "MMK": 1410.5931,
    "MNT": 2851.351567,
    "MOP": 8.021404,
    "MRO": 356.999828,
    "MRU": 35.96,
    "MUR": 39.950002,
    "MVR": 15.4,
    "MWK": 783.5543,
    "MXN": 21.482925,
    "MYR": 4.13,
    "MZN": 74.511998,
    "NAD": 15.56,
    "NGN": 413.144797,
    "NIO": 34.985262,
    "NOK": 8.527921,
    "NPR": 117.088877,
    "NXT": 33.1411107143,
    "NZD": 1.405355,
    "OMR": 0.384996,
    "PAB": 1,
    "PEN": 3.699477,
    "PGK": 3.536452,
    "PHP": 48.616922,
    "PKR": 157.360932,
    "PLN": 3.876101,
    "PYG": 6666.695466,
    "QAR": 3.641,
    "RON": 4.1217,
    "RSD": 99.318352,
    "RUB": 74.406833,
    "RWF": 995.994893,
    "SAR": 3.751686,
    "SBD": 7.98288,
    "SCR": 21.205016,
    "SDG": 379.5,
    "SEK": 8.573861,
    "SGD": 1.350235,
    "SHP": 0.722792,
    "SLL": 10199.250129,
    "SOS": 579.882945,
    "SRD": 14.154,
    "SSP": 130.26,
    "STD": 20337.466992,
    "STN": 20.85,
    "STR": 2.3642066242,
    "SVC": 8.754405,
    "SYP": 512.847239,
    "SZL": 15.519778,
    "THB": 30.84,
    "TJS": 11.399778,
    "TMT": 3.5,
    "TND": 2.7565,
    "TOP": 2.292615,
    "TRY": 7.690379,
    "TTD": 6.790838,
    "TWD": 28.360401,
    "TZS": 2319,
    "UAH": 27.779239,
    "UGX": 3670.910984,
    "USD": 1,
    "UYU": 44.322079,
    "UZS": 10503.31249,
    "VEF_BLKMKT": 1883762.14,
    "VEF_DICOM": 1889184.91,
    "VEF_DIPRO": 105039407.05,
    "VES": 1885675.5,
    "VND": 23054.379854,
    "VUV": 108.545673,
    "WST": 2.511236,
    "XAF": 553.191125,
    "XAG": 0.03944151,
    "XAU": 0.00059074,
    "XCD": 2.70255,
    "XDR": 0.701579,
    "XMR": 0.0045021474,
    "XOF": 553.191125,
    "XPD": 0.00042994,
    "XPF": 100.636567,
    "XPT": 0.00086951,
    "XRP": 2.0806078475,
    "YER": 250.399984,
    "ZAR": 15.479882,
    "ZMW": 21.934231,
    "ZWL": 322
  }
}