{
  "disclaimer": "Usage subject to terms: https://openexchangerates.org/terms",
  "license": "https://openexchangerates.org/license",
  "timestamp": 1567468800,
  "base": "USD",
  "rates": {
    "AED": 3.673181,
    "AFN": 77.9205,
    "ALL": 111.26,
    "AMD": 476.134179,
    "ANG": 1.784389,
    "AOA": 362.0025,
    "ARS": 58.2555,
    "AUD": 1.48995,
    "AWG": 1.8,
    "AZN": 1.7025,
    "BAM": 1.78285,
    "BBD": 2,
    "BDT": 84.466497,
    "BGN": 1.78314,
    "BHD": 0.376969,
    "BIF": 1852.640523,
    "BMD": 1,
    "BND": 1.350567,
    "BOB": 6.92565,
    "BRL": 4.1859,
    "BSD": 1,
    "BTC": 0.000096236974,
    "BTN": 71.383322,
    "BTS": 29.893171118,
    "BWP": 11.082902,
    "BYN": 2.110544,
    "BZD": 2.015004,
    "CAD": 1.333445,
    "CDF": 1664.427222,
    "CHF": 0.990673,
    "CLF": 0.025136,
    "CLP": 725.49,
    "CNH": 7.192694,
    "CNY": 7.172,
    "COP": 3443.301234,
    "CRC": 569.174446,
    "CUC": 1,
    "CUP": 25.75,
    "CVE": 100.65,
    "CZK": 23.614185,
    "DASH": 0.0122906269,
    "DJF": 178.05,
    "DKK": 6.800408,
    "DOGE": 401.0667125,
    "DOP": 51.545,
    "DZD": 120.546066,
    "EAC": 2867.98535556,
    "EGP": 16.559,
    "EMC": 1.2125648612,
    "ERN": 14.999589,
    "ETB": 29.148116,
    "ETH": 0.0055925284,
    "EUR": 0.912117,
    "FCT": 0.3105032613,
    "FJD": 2.189706,
    "FKP": 0.828844,
    "FTC": 22.4451027826,
    "GBP": 0.828844,
    "GEL": 2.94,
    "GGP": 0.828844,
    "GHS": 5.473174,
    "GIP": 0.828844,
    "GMD": 50.49,
    "GNF": 9178.378644,
    "GTQ": 7.682429,
    "GYD": 209.139709,
    "HKD": 7.842105,
    "HNL": 24.514591,
    "HRK": 6.753482,
    "HTG": 95.314208,
    "HUF": 302.24,
    "IDR": 14276.443892,
    "ILS": 3.5408,
    "IMP": 0.828844,
    "INR": 71.972,
    "IQD": 1192.763877,
    "IRR": 42105,
    "ISK": 126.68,
    "JEP": 0.828844,
    "JMD": 135.454223,
    "JOD": 0.709001,
    "JPY": 106.17966077,
    "KES": 103.552887,
    "KGS": 69.656201,
    "KHR": 4105.963755,
    "KMF": 448.049592,
    "KPW": 900,
    "KRW": 1213.769822,
    "KWD": 0.303816,
    "KYD": 0.83298,
    "KZT": 388.272895,
    "LAK": 8769.054883,
    "LBP": 1515.45,
    "LD": 303.2,
    "LKR": 179.788296,
    "LRD": 207.725217,
    "LSL": 15.22498,
    "LTC": 0.0148787383,
    "LYD": 1.409648,
    "MAD": 9.668,
    "MDL": 17.724305,
    "MGA": 3732.734811,
    "MKD": 56.052049,
    "MMK": 1522.949042,
    "MNT": 2665.685446,
    "MOP": 8.114755,
    "MRO": 357,
    "MRU": 37.318,
    "MUR": 36.2475,
    "MVR": 15.449981,
    "MWK": 724.995,
    "MXN": 20.13,
    "MYR": 4.2216,
    "MZN": 61.345,
    "NAD": 15.22498,
    "NGN": 362.63,
    "NIO": 33.513638,
    "NMC": 3.2262324937,
    "NOK": 9.1135,
    "NPR": 114.21008,
    "NVC": 0.3852517642,
    "NXT": 65.0378452703,
    "NZD": 1.586269,
    "OMR": 0.38502,
    "PAB": 1,
    "PEN": 3.397255,
    "PGK": 3.40355,
    "PHP": 52.24797,
    "PKR": 156.75,
    "PLN": 3.97835,
    "PPC": 2.5433167196,
    "PYG": 6249.754436,
    "QAR": 3.640999,
    "RON": 4.30869,
    "RSD": 107.213194,
    "RUB": 66.7752,
    "RWF": 920.329737,
    "SAR": 3.7507,
    "SBD": 8.142811,
    "SCR": 13.690938,
    "SDG": 45.096946,
    "SEK": 9.831939,
    "SGD": 1.391612,
    "SHP": 0.828844,
    "SLL": 7288.043496,
    "SOS": 578.288572,
    "SRD": 7.458,
    "SSP": 130.26,
    "STD": 21560.79,
    "STN": 22.4,
    "STR": 15.8055847291,
    "SVC": 8.746406,
    "SYP": 515.125137,
    "SZL": 15.219514,
    "THB": 30.64,
    "TJS": 9.691743,
    "TMT": 3.50998,
    "TND": 2.877815,
    "TOP": 2.3289,
    "TRY": 5.8082,
    "TTD": 6.81045,
    "TWD": 31.376001,
    "TZS": 2298.959334,
    "UAH": 25.276,
    "UGX": 3683.236806,
    "USD": 1,
    "UYU": 36.623346,
    "UZS": 9370.831752,
    "VEF": 248487.642241,
    "VEF_BLKMKT": 26012.82,
    "VEF_DICOM": 22186.89,
    "VEF_DIPRO": 10,
    "VES": 17576.25,
    "VND": 23189.574263,
    "VTC": 3.587626202,
    "VUV": 116.747017,
    "WST": 2.652378,
    "XAF": 598.309858,
    "XAG": 0.05435675,
    "XAU": 0.00065516,
    "XCD": 2.70255,
    "XDR": 0.731955,
    "XMR": 0.0136361205,
    "XOF": 598.309858,
    "XPD": 0.00065138,
    "XPF": 108.84457,
    "XPM": 7.7563264303,
    "XPT": 0.00107559,
    "XRP": 3.8211993251,
    "YER": 250.350747,
    "ZAR": 15.249366,
    "ZMW": 13.101,
    "ZWL": 322.000001
  }
}