{
  "disclaimer": "Usage subject to terms: https://openexchangerates.org/terms",
  "license": "https://openexchangerates.org/license",
  "timestamp": 1546545600,
  "base": "USD",
  "rates": {
    "AED": 3.673096,
    "AFN": 75.349867,
    "ALL": 108.4,
    "AMD": 485.184111,
    "ANG": 1.774713,
    "AOA": 308.9205,
    "ARS": 37.4585,
    "AUD": 1.428097,
    "AWG": 1.799996,
    "AZN": 1.7025,
    "BAM": 1.71127,
    "BBD": 2,
    "BDT": 83.962,
    "BGN": 1.71714,
    "BHD": 0.376965,
    "BIF": 1810,
    "BMD": 1,
    "BND": 1.575829,
    "BOB": 6.90895,
    "BRL": 3.758782,
    "BSD": 1,
    "BTC": 0.000263055179,
    "BTN": 70.176661,
    "BTS": 25.3027256731,
    "BWP": 10.790076,
    "BYN": 2.183176,
    "BZD": 2.015404,
    "CAD": 1.347771,
    "CDF": 1631,
    "CHF": 0.988529,
    "CLF": 0.024214,
    "CLP": 693.890297,
    "CNH": 6.878793,
    "CNY": 6.872,
    "COP": 3225.15543,
    "CRC": 604.91961,
    "CUC": 1,
    "CUP": 25.75,
    "CVE": 97.3615,
    "CZK": 22.528925,
    "DASH": 0.0124139912,
    "DJF": 178,
    "DKK": 6.55517,
    "DOGE": 431.390732787,
    "DOP": 50.485,
    "DZD": 118.593212,
    "EAC": 2867.98535556,
    "EGP": 17.911,
    "EMC": 1.2125648612,
    "ERN": 14.997343,
    "ETB": 28.435,
    "ETH": 0.0068397114,
    "EUR": 0.877852,
    "FCT": 0.1223376788,
    "FJD": 2.1506,
    "FKP": 0.791646,
    "FTC": 22.4451027826,
    "GBP": 0.791646,
    "GEL": 2.665,
    "GGP": 0.791646,
    "GHS": 4.895,
    "GIP": 0.791646,
    "GMD": 49.425,
    "GNF": 9200,
    "GTQ": 7.731423,
    "GYD": 208.856309,
    "HKD": 7.830586,
    "HNL": 24.479979,
    "HRK": 6.5264,
    "HTG": 77.60981,
    "HUF": 281.6915,
    "IDR": 14365.029772,
    "ILS": 3.7275,
    "IMP": 0.791646,
    "INR": 70.065,
    "IQD": 1191,
    "IRR": 42105,
    "ISK": 117.449772,
    "JEP": 0.791646,
    "JMD": 127.68,
    "JOD": 0.709603,
    "JPY": 107.7365,
    "KES": 102.203579,
    "KGS": 68.707788,
    "KHR": 4016,
    "KMF": 433.30205,
    "KPW": 900,
    "KRW": 1125.38,
    "KWD": 0.303451,
    "KYD": 0.833189,
    "KZT": 380.83,
    "LAK": 8557.5,
    "LBP": 1510.497727,
    "LD": 254.65,
    "LKR": 182.86235,
    "LRD": 157.500158,
    "LSL": 14.45,
    "LTC": 0.0322216852,
    "LYD": 1.395,
    "MAD": 9.534659,
    "MDL": 17.142459,
    "MGA": 3485,
    "MKD": 54.160426,
    "MMK": 1544.190086,
    "MNT": 2453.75,
    "MOP": 8.065207,
    "MRO": 357,
    "MRU": 36.37,
    "MUR": 34.501,
    "MVR": 15.459996,
    "MWK": 738.989493,
    "MXN": 19.58845,
    "MYR": 4.144993,
    "MZN": 61.500523,
    "NAD": 14.42,
    "NGN": 364.5,
    "NIO": 32.44,
    "NMC": 1.5283328319,
    "NOK": 8.68737,
    "NPR": 112.279324,
    "NVC": 0.3852517642,
    "NXT": 35.8512734332,
    "NZD": 1.494528,
    "OMR": 0.384945,
    "PAB": 1,
    "PEN": 3.373037,
    "PGK": 3.36,
    "PHP": 52.563799,
    "PKR": 139.85,
    "PLN": 3.76629,
    "PPC": 1.50370484,
    "PYG": 5979.114987,
    "QAR": 3.640999,
    "RON": 4.093091,
    "RSD": 103.889915,
    "RUB": 68.6248,
    "RWF": 875,
    "SAR": 3.7509,
    "SBD": 8.269548,
    "SCR": 13.64263,
    "SDG": 47.46,
    "SEK": 9.00428,
    "SGD": 1.364222,
    "SHP": 0.791646,
    "SLL": 8390,
    "SOS": 580,
    "SRD": 7.458,
    "SSP": 130.2634,
    "STD": 21050.59961,
    "STN": 21.5,
    "STR": 8.8871444444,
    "SVC": 8.748141,
    "SYP": 514.989954,
    "SZL": 14.45,
    "THB": 32.216517,
    "TJS": 9.431219,
    "TMT": 3.499986,
    "TND": 2.949605,
    "TOP": 2.279305,
    "TRY": 5.45762,
    "TTD": 6.77945,
    "TWD": 30.899981,
    "TZS": 2300,
    "UAH": 27.721,
    "UGX": 3724.425588,
    "USD": 1,
    "UYU": 32.459441,
    "UZS": 8335,
    "VEF": 248487.642241,
    "VEF_BLKMKT": 810.96,
    "VEF_DICOM": 642.85,
    "VEF_DIPRO": 10,
    "VES": 637.5846,
    "VND": 23099.488934,
    "VTC": 3.6814262311,
    "VUV": 111.596423,
    "WST": 2.613201,
    "XAF": 575.832898,
    "XAG": 0.06356481,
    "XAU": 0.00077346,
    "XCD": 2.70255,
    "XDR": 0.717633,
    "XMR": 0.0199995947,
    "XOF": 575.832898,
    "XPD": 0.00079056,
    "XPF": 104.75556,
    "XPM": 5.2409549293,
    "XPT": 0.00125396,
    "XRP": 2.781201661,
    "YER": 250.300682,
    "ZAR": 14.288116,
    "ZMW": 11.999,
    "ZWL": 322.355011
  }
}