{
  "disclaimer": "Usage subject to terms: https://openexchangerates.org/terms",
  "license": "https://openexchangerates.org/license",
  "timestamp": 1554249600,
  "base": "USD",
  "rates": {
    "AED": 3.673181,
    "AFN": 76.248356,
    "ALL": 111.844609,
    "AMD": 486.287277,
    "ANG": 1.844845,
    "AOA": 317.6255,
    "ARS": 42.716,
    "AUD": 1.41693,
    "AWG": 1.800999,
    "AZN": 1.7025,
    "BAM": 1.746307,
    "BBD": 2,
    "BDT": 84.236812,
    "BGN": 1.74582,
    "BHD": 0.376988,
    "BIF": 1831.231838,
    "BMD": 1,
    "BND": 1.350802,
    "BOB": 6.910406,
    "BRL": 3.853794,
    "BSD": 1,
    "BTC": 0.000203802225,
    "BTN": 68.98895,
    "BTS": 14.6137670251,
    "BWP": 10.650105,
    "BYN": 2.143461,
    "BZD": 2.015874,
    "CAD": 1.334427,
    "CDF": 1640.574,
    "CHF": 0.998192,
    "CLF": 0.024214,
    "CLP": 673.400722,
    "CNH": 6.726311,
    "CNY": 6.723384,
    "COP": 3141.486037,
    "CRC": 598.145317,
    "CUC": 1,
    "CUP": 25.75,
    "CVE": 98.75875,
    "CZK": 22.974055,
    "DASH": 0.0080002491,
    "DJF": 178.05,
    "DKK": 6.663312,
    "DOGE": 357.652719298,
    "DOP": 50.649129,
    "DZD": 119.575135,
    "EAC": 2867.98535556,
    "EGP": 17.32,
    "EMC": 1.2125648612,
    "ERN": 14.996682,
    "ETB": 28.696384,
    "ETH": 0.0060574855,
    "EUR": 0.892586,
    "FCT": 0.1199188529,
    "FJD": 2.131801,
    "FKP": 0.761794,
    "FTC": 22.4451027826,
    "GBP": 0.761794,
    "GEL": 2.69,
    "GGP": 0.761794,
    "GHS": 5.370229,
    "GIP": 0.761794,
    "GMD": 49.6025,
    "GNF": 9164.681462,
    "GTQ": 7.68056,
    "GYD": 209.29404,
    "HKD": 7.84955,
    "HNL": 24.54822,
    "HRK": 6.6317,
    "HTG": 83.968502,
    "HUF": 286.722249,
    "IDR": 14220.001005,
    "ILS": 3.6242,
    "IMP": 0.761794,
    "INR": 68.92,
    "IQD": 1191.833087,
    "IRR": 42105,
    "ISK": 121.489854,
    "JEP": 0.761794,
    "JMD": 125.456984,
    "JOD": 0.709001,
    "JPY": 111.30949982,
    "KES": 100.796485,
    "KGS": 68.708343,
    "KHR": 4027.311717,
    "KMF": 439.550624,
    "KPW": 900,
    "KRW": 1137.39,
    "KWD": 0.304591,
    "KYD": 0.833195,
    "KZT": 379.604795,
    "LAK": 8627.929377,
    "LBP": 1510.78418,
    "LD": 264,
    "LKR": 174.55,
    "LRD": 162.999986,
    "LSL": 14.148258,
    "LTC": 0.0128932439,
    "LYD": 1.391378,
    "MAD": 9.6724,
    "MDL": 17.311615,
    "MGA": 3595.163881,
    "MKD": 55.025036,
    "MMK": 1510.397971,
    "MNT": 2512.83157,
    "MOP": 8.084746,
    "MRO": 357,
    "MRU": 36.6,
    "MUR": 35.0485,
    "MVR": 15.459996,
    "MWK": 723.984738,
    "MXN": 19.2309,
    "MYR": 4.091,
    "MZN": 64.551215,
    "NAD": 14.324344,
    "NGN": 359.511744,
    "NIO": 32.869466,
    "NMC": 1.1192601845,
    "NOK": 8.60287,
    "NPR": 110.383875,
    "NVC": 0.3852517642,
    "NXT": 26.203348329,
    "NZD": 1.481482,
    "OMR": 0.384996,
    "PAB": 1,
    "PEN": 3.312031,
    "PGK": 3.374658,
    "PHP": 52.475534,
    "PKR": 140.3425,
    "PLN": 3.835005,
    "PPC": 1.7383989938,
    "PYG": 6181.452661,
    "QAR": 3.641219,
    "RON": 4.247524,
    "RSD": 105.283296,
    "RUB": 65.3579,
    "RWF": 903.004116,
    "SAR": 3.750365,
    "SBD": 8.072113,
    "SCR": 13.659636,
    "SDG": 47.622495,
    "SEK": 9.327564,
    "SGD": 1.355701,
    "SHP": 0.761794,
    "SLL": 8390,
    "SOS": 579.503529,
    "SRD": 7.458,
    "SSP": 130.2634,
    "STD": 21050.59961,
    "STN": 21.89,
    "STR": 8.14470835,
    "SVC": 8.750339,
    "SYP": 514.993257,
    "SZL": 14.15519,
    "THB": 31.77,
    "TJS": 9.437923,
    "TMT": 3.50998,
    "TND": 3.032037,
    "TOP": 2.262773,
    "TRY": 5.618207,
    "TTD": 6.777011,
    "TWD": 30.844,
    "TZS": 2310.405919,
    "UAH": 27.177829,
    "UGX": 3720.252931,
    "USD": 1,
    "UYU": 33.457823,
    "UZS": 8420.233654,
    "VEF": 248487.642241,
    "VEF_BLKMKT": 3705.51,
    "VEF_DICOM": 3300.27,
    "VEF_DIPRO": 10,
    "VES": 3290.18,
    "VND": 23191.752254,
    "VTC": 1.7247212352,
    "VUV": 111.231028,
    "WST": 2.608446,
    "XAF": 585.498153,
    "XAG": 0.06615956,
    "XAU": 0.00077408,
    "XCD": 2.70255,
    "XDR": 0.718456,
    "XMR": 0.0143469322,
    "XOF": 585.498153,
    "XPD": 0.00069881,
    "XPF": 106.513864,
    "XPM": 3.2205695103,
    "XPT": 0.00117465,
    "XRP": 2.8155194378,
    "YER": 250.350747,
    "ZAR": 14.215956,
    "ZMW": 12.125697,
    "ZWL": 322.355011
  }
}