{
  "disclaimer": "Usage subject to terms: https://openexchangerates.org/terms",
  "license": "https://openexchangerates.org/license",
  "timestamp": 1588186800,
  "base": "USD",
  "rates": {
    "AED": 3.67305,
    "AFN": 76.249998,
    "ALL": 113.8,
    "AMD": 479.82041,
    "ANG": 1.795819,
    "AOA": 560,
    "ARS": 66.742554,
    "AUD": 1.528701,
    "AWG": 1.8,
    "AZN": 1.7025,
    "BAM": 1.803265,
    "BBD": 2,
    "BDT": 84.906023,
    "BGN": 1.799066,
    "BHD": 0.378094,
    "BIF": 1905.621935,
    "BMD": 1,
    "BND": 1.415176,
    "BOB": 6.907953,
    "BRL": 5.365811,
    "BSD": 1,
    "BTC": 0.00011596931,
    "BTN": 75.770824,
    "BTS": 49.7947399142,
    "BWP": 12.170942,
    "BYN": 2.435648,
    "BZD": 2.016587,
    "CAD": 1.38981,
    "CDF": 1729.767648,
    "CHF": 0.975506,
    "CLF": 0.030577,
    "CLP": 834.599428,
    "CNH": 7.07317,
    "CNY": 7.0769,
    "COP": 4028.154722,
    "CRC": 567.017672,
    "CUC": 1,
    "CUP": 25.75,
    "CVE": 102.125,
    "CZK": 24.935,
    "DASH": 0.0118574172,
    "DJF": 178,
    "DKK": 6.860522,
    "DOGE": 414.363371429,
    "DOP": 54.45,
    "DZD": 128.196,
    "EAC": 2867.98535556,
    "EGP": 15.749293,
    "EMC": 1.2125648612,
    "ERN": 14.999702,
    "ETB": 33.249203,
    "ETH": 0.0046539768,
    "EUR": 0.919796,
    "FCT": 0.5715065711,
    "FJD": 2.2447,
    "FKP": 0.803145,
    "FTC": 22.4451027826,
    "GBP": 0.803145,
    "GEL": 3.215,
    "GGP": 0.803145,
    "GHS": 5.802508,
    "GIP": 0.803145,
    "GMD": 51,
    "GNF": 9455,
    "GTQ": 7.718223,
    "GYD": 209.284552,
    "HKD": 7.75007,
    "HNL": 24.815413,
    "HRK": 6.96432,
    "HTG": 97.843451,
    "HUF": 325.248799,
    "IDR": 15165.05,
    "ILS": 3.49858,
    "IMP": 0.803145,
    "INR": 75.334995,
    "IQD": 1190.5,
    "IRR": 42105,
    "ISK": 146.60001,
    "JEP": 0.803145,
    "JMD": 141.533399,
    "JOD": 0.709,
    "JPY": 106.5902,
    "KES": 107.257345,
    "KGS": 79.66175,
    "KHR": 4075,
    "KMF": 454.974956,
    "KPW": 900,
    "KRW": 1211.82,
    "KWD": 0.309522,
    "KYD": 0.833668,
    "KZT": 429.695634,
    "LAK": 8981,
    "LBP": 1513.664537,
    "LD": 320,
    "LKR": 192.081441,
    "LRD": 197.999977,
    "LSL": 18.526467,
    "LTC": 0.0206696982,
    "LYD": 1.415,
    "MAD": 9.9175,
    "MDL": 18.003512,
    "MGA": 3802,
    "MKD": 56.808694,
    "MMK": 1414.626826,
    "MNT": 2787.291301,
    "MOP": 7.986502,
    "MRO": 357,
    "MRU": 37.475,
    "MUR": 40.106337,
    "MVR": 15.45,
    "MWK": 737.5,
    "MXN": 23.81175,
    "MYR": 4.3435,
    "MZN": 67.625001,
    "NAD": 18.985,
    "NGN": 390,
    "NIO": 34.149917,
    "NMC": 3.2262324937,
    "NOK": 10.34535,
    "NPR": 121.220103,
    "NVC": 0.3852517642,
    "NXT": 89.9393364341,
    "NZD": 1.632493,
    "OMR": 0.385072,
    "PAB": 1,
    "PEN": 3.3715,
    "PGK": 3.483484,
    "PHP": 50.36,
    "PKR": 161.5,
    "PLN": 4.183255,
    "PPC": 2.5433167196,
    "PYG": 6535.324663,
    "QAR": 3.641,
    "RON": 4.455,
    "RSD": 108.25,
    "RUB": 73.1278,
    "RWF": 935,
    "SAR": 3.758508,
    "SBD": 8.335649,
    "SCR": 15.638912,
    "SDG": 55.325,
    "SEK": 9.857437,
    "SGD": 1.411669,
    "SHP": 0.803145,
    "SLL": 9702.500123,
    "SOS": 581,
    "SRD": 7.458,
    "SSP": 130.26,
    "STD": 22050.693068,
    "STN": 22.75,
    "STR": 14.0974172539,
    "SVC": 8.753417,
    "SYP": 513.030148,
    "SZL": 18.63,
    "THB": 32.402001,
    "TJS": 10.249259,
    "TMT": 3.51,
    "TND": 2.9025,
    "TOP": 2.31435,
    "TRY": 6.952115,
    "TTD": 6.76071,
    "TWD": 29.858,
    "TZS": 2315.063219,
    "UAH": 26.98548,
    "UGX": 3805.717305,
    "USD": 1,
    "UYU": 43.492452,
    "UZS": 10116.893679,
    "VEF": 248487.642241,
    "VEF_BLKMKT": 185004.12,
    "VEF_DICOM": 175659.84,
    "VEF_DIPRO": 10058929.07,
    "VES": 175385.321794,
    "VND": 23384.723914,
    "VTC": 6.8084886676,
    "VUV": 121.637347,
    "WST": 2.77074,
    "XAF": 603.346611,
    "XAG": 0.06574648,
    "XAU": 0.00058682,
    "XCD": 2.70255,
    "XDR": 0.732815,
    "XMR": 0.0151659239,
    "XOF": 603.346611,
    "XPD": 0.00051295,
    "XPF": 109.760857,
    "XPM": 21.0235762811,
    "XPT": 0.0012866,
    "XRP": 4.4640917276,
    "YER": 250.300053,
    "ZAR": 18.150765,
    "ZMW": 18.666427,
    "ZWL": 322.000001
  }
}