{
  "disclaimer": "Usage subject to terms: https://openexchangerates.org/terms",
  "license": "https://openexchangerates.org/license",
  "timestamp": 1579788000,
  "base": "USD",
  "rates": {
    "AED": 3.6732,
    "AFN": 77.820905,
    "ALL": 110.002257,
    "AMD": 478.413264,
    "ANG": 1.673407,
    "AOA": 493.218,
    "ARS": 60.0837,
    "AUD": 1.456357,
    "AWG": 1.8,
    "AZN": 1.7025,
    "BAM": 1.7632,
    "BBD": 2,
    "BDT": 84.892322,
    "BGN": 1.76369,
    "BHD": 0.37696,
    "BIF": 1881.438624,
    "BMD": 1,
    "BND": 1.34913,
    "BOB": 6.914799,
    "BRL": 4.1605,
    "BSD": 1,
    "BTC": 0.000120225566,
    "BTN": 71.219505,
    "BTS": 54.110681982,
    "BWP": 10.729475,
    "BYN": 2.111337,
    "BZD": 2.015625,
    "CAD": 1.31605,
    "CDF": 1690.203311,
    "CHF": 0.967274,
    "CLF": 0.02796,
    "CLP": 768.7,
    "CNH": 6.929371,
    "CNY": 6.9329,
    "COP": 3331.38,
    "CRC": 562.462102,
    "CUC": 1,
    "CUP": 25.75,
    "CVE": 99.65,
    "CZK": 22.6891,
    "DASH": 0.0099040734,
    "DJF": 178.05,
    "DKK": 6.74068,
    "DOGE": 444.910051852,
    "DOP": 53.18799,
    "DZD": 119.606981,
    "EAC": 2867.98535556,
    "EGP": 15.7877,
    "EMC": 1.2125648612,
    "ERN": 14.999645,
    "ETB": 32.05,
    "ETH": 0.0062270378,
    "EUR": 0.901984,
    "FCT": 0.5715065711,
    "FJD": 2.17115,
    "FKP": 0.761692,
    "FTC": 22.4451027826,
    "GBP": 0.761692,
    "GEL": 2.885,
    "GGP": 0.761692,
    "GHS": 5.66215,
    "GIP": 0.761692,
    "GMD": 51.25,
    "GNF": 9535.833945,
    "GTQ": 7.689762,
    "GYD": 209.127363,
    "HKD": 7.772636,
    "HNL": 24.626607,
    "HRK": 6.7154,
    "HTG": 99.194379,
    "HUF": 304.186969,
    "IDR": 13633.373893,
    "ILS": 3.4571,
    "IMP": 0.761692,
    "INR": 71.328895,
    "IQD": 1193.775262,
    "IRR": 42104.44504,
    "ISK": 124.289973,
    "JEP": 0.761692,
    "JMD": 139.001071,
    "JOD": 0.709,
    "JPY": 109.53265096,
    "KES": 100.81,
    "KGS": 69.61535,
    "KHR": 4048.3822,
    "KMF": 444.59996,
    "KPW": 900,
    "KRW": 1167.74,
    "KWD": 0.303703,
    "KYD": 0.8333,
    "KZT": 378.002873,
    "LAK": 8877.286501,
    "LBP": 1512.144558,
    "LD": 320,
    "LKR": 181.51923,
    "LRD": 193.999927,
    "LSL": 14.379896,
    "LTC": 0.0182481752,
    "LYD": 1.401217,
    "MAD": 9.614875,
    "MDL": 17.652344,
    "MGA": 3686.840076,
    "MKD": 55.582371,
    "MMK": 1467.455954,
    "MNT": 2704.459096,
    "MOP": 8.004707,
    "MRO": 357,
    "MRU": 37.492901,
    "MUR": 36.622272,
    "MVR": 15.475,
    "MWK": 736.388455,
    "MXN": 18.710958,
    "MYR": 4.07,
    "MZN": 63.17,
    "NAD": 14.379896,
    "NGN": 361.685832,
    "NIO": 33.734113,
    "NMC": 3.2262324937,
    "NOK": 8.994809,
    "NPR": 113.951589,
    "NVC": 0.3852517642,
    "NXT": 93.8482140625,
    "NZD": 1.514343,
    "OMR": 0.385006,
    "PAB": 1,
    "PEN": 3.318412,
    "PGK": 3.451765,
    "PHP": 50.9495,
    "PKR": 154.720201,
    "PLN": 3.82855,
    "PPC": 2.5433167196,
    "PYG": 6526.788698,
    "QAR": 3.640929,
    "RON": 4.3115,
    "RSD": 106.015,
    "RUB": 61.9375,
    "RWF": 949.27323,
    "SAR": 3.751308,
    "SBD": 8.28728,
    "SCR": 13.700398,
    "SDG": 45.325003,
    "SEK": 9.510261,
    "SGD": 1.349881,
    "SHP": 0.761692,
    "SLL": 7488.043446,
    "SOS": 578.409237,
    "SRD": 7.458,
    "SSP": 130.26,
    "STD": 21560.79,
    "STN": 22.25,
    "STR": 17.2346791966,
    "SVC": 8.749555,
    "SYP": 515.20941,
    "SZL": 14.379896,
    "THB": 30.544667,
    "TJS": 9.693216,
    "TMT": 3.51,
    "TND": 2.823,
    "TOP": 2.299983,
    "TRY": 5.933325,
    "TTD": 6.76152,
    "TWD": 30.033998,
    "TZS": 2305.585823,
    "UAH": 24.375548,
    "UGX": 3677.336557,
    "USD": 1,
    "UYU": 37.320167,
    "UZS": 9567.23422,
    "VEF": 248487.642241,
    "VEF_BLKMKT": 76332.04,
    "VEF_DICOM": 73701.08,
    "VEF_DIPRO": 4261787,
    "VES": 33474.855,
    "VND": 23177.498946,
    "VTC": 6.8084886676,
    "VUV": 115.781421,
    "WST": 2.632013,
    "XAF": 591.662633,
    "XAG": 0.0564176,
    "XAU": 0.00064222,
    "XCD": 2.70255,
    "XDR": 0.724877,
    "XMR": 0.0162492342,
    "XOF": 591.662633,
    "XPD": 0.00041397,
    "XPF": 107.635307,
    "XPM": 21.0235762811,
    "XPT": 0.00099575,
    "XRP": 4.4474533136,
    "YER": 250.349961,
    "ZAR": 14.371,
    "ZMW": 14.497363,
    "ZWL": 322.000001
  }
}