{
  "disclaimer": "Usage subject to terms: https://openexchangerates.org/terms",
  "license": "https://openexchangerates.org/license",
  "timestamp": 1658872800,
  "base": "USD",
  "rates": {
    "AED": 3.67303,
    "AFN": 90.3548,
    "ALL": 114.860662,
    "AMD": 407.464621,
    "ANG": 1.801842,
    "AOA": 432.29295,
    "ARS": 130.59417,
    "AUD": 1.440818,
    "AWG": 1.79375,
    "AZN": 1.7,
    "BAM": 1.92649,
    "BBD": 2,
    "BDT": 94.705369,
    "BGN": 1.934415,
    "BHD": 0.377069,
    "BIF": 2059.811679,
    "BMD": 1,
    "BND": 1.388335,
    "BOB": 6.883538,
    "BRL": 5.3515,
    "BSD": 1,
    "BTC": 0.000047771035,
    "BTN": 79.690601,
    "BTS": 95.581096,
    "BWP": 12.641076,
    "BYN": 2.523862,
    "BZD": 2.015504,
    "CAD": 1.288319,
    "CDF": 1999.963021,
    "CHF": 0.9631,
    "CLF": 0.033519,
    "CLP": 924.9,
    "CNH": 6.76735,
    "CNY": 6.7632,
    "COP": 4481.433531,
    "CRC": 671.551251,
    "CUC": 1,
    "CUP": 25.75,
    "CVE": 108.672952,
    "CZK": 24.31,
    "DASH": 0.0232901947,
    "DJF": 178.008944,
    "DKK": 7.355599,
    "DOGE": 16.3666260274,
    "DOP": 54.319202,
    "DZD": 146.171146,
    "EGP": 18.9595,
    "ERN": 15,
    "ETB": 52.602852,
    "ETH": 0.00072575,
    "EUR": 0.988277,
    "FJD": 2.2008,
    "FKP": 0.831166,
    "GBP": 0.831166,
    "GEL": 2.939685,
    "GGP": 0.831166,
    "GHS": 8.274283,
    "GIP": 0.831166,
    "GMD": 54.061001,
    "GNF": 8656.710518,
    "GTQ": 7.734307,
    "GYD": 209.169262,
    "HKD": 7.849298,
    "HNL": 24.598366,
    "HRK": 7.4255,
    "HTG": 116.363832,
    "HUF": 396.4975,
    "IDR": 14990.25,
    "ILS": 3.445855,
    "IMP": 0.831166,
    "INR": 79.8431,
    "IQD": 1459.408342,
    "IRR": 42350.000166,
    "ISK": 137.47,
    "JEP": 0.831166,
    "JMD": 152.846177,
    "JOD": 0.709,
    "JPY": 136.9145,
    "KES": 118.6,
    "KGS": 80.36095,
    "KHR": 4095.618116,
    "KMF": 474.87801,
    "KPW": 900,
    "KRW": 1310.752089,
    "KWD": 0.307196,
    "KYD": 0.83321,
    "KZT": 480.009023,
    "LAK": 15058.944028,
    "LBP": 1511.889048,
    "LD": 320,
    "LKR": 354.958068,
    "LRD": 152.425071,
    "LSL": 16.784769,
    "LTC": 0.0189778839,
    "LYD": 4.880273,
    "MAD": 10.257577,
    "MDL": 19.2802,
    "MGA": 4212.241055,
    "MKD": 60.690681,
    "MMK": 1851.335149,
    "MNT": 3148.759996,
    "MOP": 8.083864,
    "MRU": 37.266432,
    "MUR": 44.70665,
    "MVR": 15.355024,
    "MWK": 1026.314153,
    "MXN": 20.463494,
    "MYR": 4.456,
    "MZN": 63.855034,
    "NAD": 16.323954,
    "NGN": 421.529813,
    "NIO": 35.90221,
    "NOK": 9.90328,
    "NPR": 127.50413,
    "NXT": 341.361057143,
    "NZD": 1.604578,
    "OMR": 0.385056,
    "PAB": 1,
    "PEN": 3.915793,
    "PGK": 3.523965,
    "PHP": 55.466501,
    "PKR": 232.854387,
    "PLN": 4.701201,
    "PYG": 6896.540548,
    "QAR": 3.672997,
    "RON": 4.8742,
    "RSD": 116.066956,
    "RUB": 60.125004,
    "RWF": 1033.033722,
    "SAR": 3.75737,
    "SBD": 8.14525,
    "SCR": 12.800791,
    "SDG": 456.500715,
    "SEK": 10.315142,
    "SGD": 1.3898,
    "SHP": 0.831166,
    "SLL": 13748.9,
    "SOS": 568.44266,
    "SRD": 24.1825,
    "SSP": 130.26,
    "STD": 22204.690504,
    "STN": 23.7114,
    "STR": 9.6546561616,
    "SVC": 8.748756,
    "SYP": 2512.53,
    "SZL": 16.784768,
    "THB": 36.716542,
    "TJS": 10.199068,
    "TMT": 3.501783,
    "TND": 3.122383,
    "TOP": 2.341814,
    "TRY": 17.85955,
    "TTD": 6.786231,
    "TWD": 29.9304,
    "TZS": 2331.79766,
    "UAH": 36.796785,
    "UGX": 3844.620654,
    "USD": 1,
    "UYU": 41.742194,
    "UZS": 10959.108074,
    "VEF_BLKMKT": 5.88,
    "VEF_DICOM": 5.72,
    "VEF_DIPRO": 343.46,
    "VES": 5.71407,
    "VND": 23372.677659,
    "VUV": 118.218013,
    "WST": 2.710725,
    "XAF": 648.267396,
    "XAG": 0.05370583,
    "XAU": 0.00058228,
    "XCD": 2.70255,
    "XDR": 0.734674,
    "XMR": 0.0067764366,
    "XOF": 648.267396,
    "XPD": 0.0004963,
    "XPF": 117.932849,
    "XPT": 0.00114091,
    "XRP": 3.0113766856,
    "YER": 250.272272,
    "ZAR": 16.92081,
    "ZMW": 16.798558,
    "ZWL": 322
  }
}