{
  "disclaimer": "Usage subject to terms: https://openexchangerates.org/terms",
  "license": "https://openexchangerates.org/license",
  "timestamp": 1547456400,
  "base": "USD",
  "rates": {
    "AED": 3.673028,
    "AFN": 76.259,
    "ALL": 109.544278,
    "AMD": 488.314375,
    "ANG": 1.783346,
    "AOA": 310.252,
    "ARS": 36.905408,
    "AUD": 1.390399,
    "AWG": 1.800506,
    "AZN": 1.7025,
    "BAM": 1.704093,
    "BBD": 2,
    "BDT": 84.122184,
    "BGN": 1.70633,
    "BHD": 0.376985,
    "BIF": 1802.313347,
    "BMD": 1,
    "BND": 1.356785,
    "BOB": 6.943046,
    "BRL": 3.7113,
    "BSD": 1,
    "BTC": 0.000281623408,
    "BTN": 70.777131,
    "BTS": 26.5669458491,
    "BWP": 10.531521,
    "BYN": 2.160748,
    "BZD": 2.025249,
    "CAD": 1.327391,
    "CDF": 1653.79436,
    "CHF": 0.98233,
    "CLF": 0.02338,
    "CLP": 676.887671,
    "CNH": 6.76635,
    "CNY": 6.7603,
    "COP": 3152.888031,
    "CRC": 608.602287,
    "CUC": 1,
    "CUP": 25.75,
    "CVE": 96.23025,
    "CZK": 22.268006,
    "DASH": 0.0141258459,
    "DJF": 178,
    "DKK": 6.504603,
    "DOGE": 477.304450847,
    "DOP": 50.315135,
    "DZD": 118.22,
    "EAC": 2867.98535556,
    "EGP": 17.9427,
    "EMC": 1.2125648612,
    "ERN": 14.998107,
    "ETB": 28.371836,
    "ETH": 0.0085451827,
    "EUR": 0.871445,
    "FCT": 0.1534022018,
    "FJD": 2.117803,
    "FKP": 0.779821,
    "FTC": 22.4451027826,
    "GBP": 0.779821,
    "GEL": 2.665,
    "GGP": 0.779821,
    "GHS": 5.018745,
    "GIP": 0.779821,
    "GMD": 49.5025,
    "GNF": 9162.848102,
    "GTQ": 7.764258,
    "GYD": 209.951226,
    "HKD": 7.8426,
    "HNL": 24.509616,
    "HRK": 6.4786,
    "HTG": 78.104117,
    "HUF": 279.988,
    "IDR": 14121.003184,
    "ILS": 3.667419,
    "IMP": 0.779821,
    "INR": 70.755693,
    "IQD": 1198.899741,
    "IRR": 42497.868611,
    "ISK": 120.509767,
    "JEP": 0.779821,
    "JMD": 130.110601,
    "JOD": 0.709603,
    "JPY": 108.19983333,
    "KES": 101.65,
    "KGS": 68.708377,
    "KHR": 4033.897377,
    "KMF": 427.298012,
    "KPW": 900,
    "KRW": 1122.02,
    "KWD": 0.302998,
    "KYD": 0.837319,
    "KZT": 378.579343,
    "LAK": 8598.408637,
    "LBP": 1515.370428,
    "LD": 252.35,
    "LKR": 182.818878,
    "LRD": 158.000217,
    "LSL": 13.88195,
    "LTC": 0.0331071015,
    "LYD": 1.387462,
    "MAD": 9.497167,
    "MDL": 17.124845,
    "MGA": 3601.969036,
    "MKD": 53.594957,
    "MMK": 1533.760117,
    "MNT": 2453.75,
    "MOP": 8.115011,
    "MRO": 357,
    "MRU": 36.45,
    "MUR": 34.247,
    "MVR": 15.459996,
    "MWK": 732.611173,
    "MXN": 19.15731,
    "MYR": 4.099538,
    "MZN": 61.520318,
    "NAD": 13.882528,
    "NGN": 365.99,
    "NIO": 32.638056,
    "NMC": 1.4317434847,
    "NOK": 8.555451,
    "NPR": 113.241049,
    "NVC": 0.3852517642,
    "NXT": 39.0041033241,
    "NZD": 1.469875,
    "OMR": 0.384975,
    "PAB": 1,
    "PEN": 3.357998,
    "PGK": 3.385007,
    "PHP": 52.19025,
    "PKR": 140.53466,
    "PLN": 3.742469,
    "PPC": 1.800227744,
    "PYG": 6050.498168,
    "QAR": 3.6583,
    "RON": 4.076399,
    "RSD": 103.168761,
    "RUB": 67.155,
    "RWF": 898.591107,
    "SAR": 3.7513,
    "SBD": 8.06559,
    "SCR": 13.645394,
    "SDG": 47.835493,
    "SEK": 8.936144,
    "SGD": 1.354022,
    "SHP": 0.779821,
    "SLL": 8390,
    "SOS": 581.208516,
    "SRD": 7.458,
    "SSP": 130.2634,
    "STD": 21050.59961,
    "STN": 21.275,
    "STR": 9.5850791695,
    "SVC": 8.792291,
    "SYP": 515.023278,
    "SZL": 13.881911,
    "THB": 31.955,
    "TJS": 9.47981,
    "TMT": 3.50998,
    "TND": 2.957028,
    "TOP": 2.258172,
    "TRY": 5.51508,
    "TTD": 6.804138,
    "TWD": 30.847524,
    "TZS": 2302.3,
    "UAH": 28.209737,
    "UGX": 3727.65191,
    "USD": 1,
    "UYU": 32.77838,
    "UZS": 8377.037293,
    "VEF": 248487.642241,
    "VEF_BLKMKT": 2189.47,
    "VEF_DICOM": 794.85,
    "VEF_DIPRO": 10,
    "VES": 794.471585,
    "VND": 23311.703024,
    "VTC": 4.4334009131,
    "VUV": 110.9101,
    "WST": 2.599914,
    "XAF": 571.630594,
    "XAG": 0.06406571,
    "XAU": 0.00077286,
    "XCD": 2.70255,
    "XDR": 0.71458,
    "XMR": 0.0226561622,
    "XOF": 571.630594,
    "XPD": 0.00076151,
    "XPF": 103.991077,
    "XPM": 5.7813513858,
    "XPT": 0.00124379,
    "XRP": 3.0782365449,
    "YER": 250.399354,
    "ZAR": 13.923346,
    "ZMW": 11.981544,
    "ZWL": 322.355011
  }
}