{
  "disclaimer": "Usage subject to terms: https://openexchangerates.org/terms",
  "license": "https://openexchangerates.org/license",
  "timestamp": 1593558000,
  "base": "USD",
  "rates": {
    "AED": 3.6732,
    "AFN": 77.231214,
    "ALL": 110.759679,
    "AMD": 481.616228,
    "ANG": 1.795179,
    "AOA": 578.925,
    "ARS": 70.3883,
    "AUD": 1.448927,
    "AWG": 1.8,
    "AZN": 1.7025,
    "BAM": 1.744976,
    "BBD": 2,
    "BDT": 84.903305,
    "BGN": 1.740521,
    "BHD": 0.377031,
    "BIF": 1920.307005,
    "BMD": 1,
    "BND": 1.397376,
    "BOB": 6.905655,
    "BRL": 5.4637,
    "BSD": 1,
    "BTC": 0.00010955985,
    "BTN": 75.587402,
    "BTS": 43.3067177866,
    "BWP": 11.807715,
    "BYN": 2.421409,
    "BZD": 2.015908,
    "CAD": 1.357413,
    "CDF": 1922.596469,
    "CHF": 0.947104,
    "CLF": 0.029693,
    "CLP": 822.798773,
    "CNH": 7.070155,
    "CNY": 7.0655,
    "COP": 3742.484718,
    "CRC": 579.835166,
    "CUC": 1,
    "CUP": 25.75,
    "CVE": 98.65,
    "CZK": 23.7392,
    "DASH": 0.0146986178,
    "DJF": 178.046714,
    "DKK": 6.6329,
    "DOGE": 438.263984,
    "DOP": 58.365628,
    "DZD": 128.971788,
    "EAC": 2867.98535556,
    "EGP": 16.1494,
    "EMC": 1.2125648612,
    "ERN": 15.003062,
    "ETB": 35.052463,
    "ETH": 0.0044448395,
    "EUR": 0.890051,
    "FCT": 0.5715065711,
    "FJD": 2.173,
    "FKP": 0.806846,
    "FTC": 22.4451027826,
    "GBP": 0.806846,
    "GEL": 3.07,
    "GGP": 0.806846,
    "GHS": 5.789359,
    "GIP": 0.806846,
    "GMD": 51.6,
    "GNF": 9635.524768,
    "GTQ": 7.700776,
    "GYD": 209.120836,
    "HKD": 7.75075,
    "HNL": 24.936023,
    "HRK": 6.7366,
    "HTG": 109.426458,
    "HUF": 315.654466,
    "IDR": 14607.5,
    "ILS": 3.4615,
    "IMP": 0.806846,
    "INR": 75.5535,
    "IQD": 1192.553928,
    "IRR": 42176.99,
    "ISK": 138.31,
    "JEP": 0.806846,
    "JMD": 139.868965,
    "JOD": 0.709,
    "JPY": 107.94925,
    "KES": 106.54,
    "KGS": 75.428905,
    "KHR": 4111.081316,
    "KMF": 438.65032,
    "KPW": 900,
    "KRW": 1199.4,
    "KWD": 0.307892,
    "KYD": 0.833486,
    "KZT": 405.991965,
    "LAK": 9033.691133,
    "LBP": 1515.150063,
    "LD": 320,
    "LKR": 186.234981,
    "LRD": 199.299968,
    "LSL": 17.357731,
    "LTC": 0.0243131534,
    "LYD": 1.403213,
    "MAD": 9.713326,
    "MDL": 17.009792,
    "MGA": 3863.138622,
    "MKD": 54.856417,
    "MMK": 1371.147856,
    "MNT": 2825.265872,
    "MOP": 7.983476,
    "MRO": 357,
    "MRU": 37.888048,
    "MUR": 40.15,
    "MVR": 15.41,
    "MWK": 736.357749,
    "MXN": 23.016795,
    "MYR": 4.285,
    "MZN": 70.100006,
    "NAD": 17.37,
    "NGN": 387.18181,
    "NIO": 34.073145,
    "NMC": 3.2262324937,
    "NOK": 9.622243,
    "NPR": 120.941283,
    "NVC": 0.3852517642,
    "NXT": 94.4534448276,
    "NZD": 1.549811,
    "OMR": 0.384965,
    "PAB": 1,
    "PEN": 3.5368,
    "PGK": 3.456756,
    "PHP": 49.835167,
    "PKR": 167.850782,
    "PLN": 3.957503,
    "PPC": 2.5433167196,
    "PYG": 6797.73223,
    "QAR": 3.641,
    "RON": 4.3048,
    "RSD": 104.65,
    "RUB": 71.1762,
    "RWF": 953.381139,
    "SAR": 3.751191,
    "SBD": 8.349572,
    "SCR": 17.599387,
    "SDG": 55.325,
    "SEK": 9.318699,
    "SGD": 1.393593,
    "SHP": 0.806846,
    "SLL": 9730.001494,
    "SOS": 579.551942,
    "SRD": 7.458,
    "SSP": 130.26,
    "STD": 22000.619692,
    "STN": 21.95,
    "STR": 15.0296290809,
    "SVC": 8.751511,
    "SYP": 513.193715,
    "SZL": 17.360592,
    "THB": 30.884461,
    "TJS": 10.308475,
    "TMT": 3.5,
    "TND": 2.862,
    "TOP": 2.295019,
    "TRY": 6.85203,
    "TTD": 6.749878,
    "TWD": 29.41,
    "TZS": 2318,
    "UAH": 26.680645,
    "UGX": 3728.3738,
    "USD": 1,
    "UYU": 42.067033,
    "UZS": 10185.048354,
    "VEF": 248487.642241,
    "VEF_BLKMKT": 212371.73,
    "VEF_DICOM": 202331.51,
    "VEF_DIPRO": 11937638.83,
    "VES": 202053.013256,
    "VND": 23149.550212,
    "VTC": 6.8084886676,
    "VUV": 116.140126,
    "WST": 2.704367,
    "XAF": 583.83525,
    "XAG": 0.05498735,
    "XAU": 0.00056123,
    "XCD": 2.70255,
    "XDR": 0.725868,
    "XMR": 0.0157665703,
    "XOF": 583.83525,
    "XPD": 0.00051495,
    "XPF": 106.211349,
    "XPM": 21.0235762811,
    "XPT": 0.00120483,
    "XRP": 5.7154927491,
    "YER": 250.349961,
    "ZAR": 17.3569,
    "ZMW": 18.160251,
    "ZWL": 322
  }
}